hnsqlite/__init__.py
hnsqlite/collection.py
hnsqlite/filter.py
hnsqlite/util.py
hnsqlite-0.2.4.dist-info/LICENSE
hnsqlite-0.2.4.dist-info/METADATA
hnsqlite-0.2.4.dist-info/WHEEL
hnsqlite-0.2.4.dist-info/top_level.txt
hnsqlite-0.2.4.dist-info/RECORD
