Metadata-Version: 2.1
Name: hnsqlite
Version: 0.2.4
Summary: A minimalist integration of sqlite and hnswlib focused on providing simple embedding persistence and search for text applications.
Author-email: Bill Kish <bk@jiggy.ai>
Project-URL: Homepage, https://github.com/jiggy-ai/hnsqlite
Project-URL: Bug Tracker, https://github.com/jiggy-ai/hnsqlite/issues
Classifier: Programming Language :: Python :: 3
Classifier: License :: OSI Approved :: Apache Software License
Classifier: Operating System :: OS Independent
Requires-Python: >=3.9
License-File: LICENSE
Requires-Dist: sqlmodel
Requires-Dist: hnswlib
Requires-Dist: psutil
Requires-Dist: numpy
Requires-Dist: loguru
